<?xml version="1.0" encoding="UTF-8" standalone="yes"?>
<players>
    <player>
        <level>0</level>
        <name>シフト＝キー</name>
        <sex>MAN</sex>
        <status>
            <entry>
                <key>LV</key>
                <value>
                    <key>LV</key>
                    <name>レベル</name>
                    <value>1</value>
                </value>
            </entry>
            <entry>
                <key>MP</key>
                <value>
                    <key>MP</key>
                    <name>マジックトポイント</name>
                    <value>12</value>
                </value>
            </entry>
            <entry>
                <key>AGI</key>
                <value>
                    <key>AGI</key>
                    <name>すばやさ</name>
                    <value>4</value>
                </value>
            </entry>
            <entry>
                <key>LUK</key>
                <value>
                    <key>LUK</key>
                    <name>うんのよさ</name>
                    <value>10</value>
                </value>
            </entry>
            <entry>
                <key>HP</key>
                <value>
                    <key>HP</key>
                    <name>ヒットポイント</name>
                    <value>12</value>
                </value>
            </entry>
            <entry>
                <key>POW</key>
                <value>
                    <key>POW</key>
                    <name>ちから</name>
                    <value>6</value>
                </value>
            </entry>
            <entry>
                <key>INT</key>
                <value>
                    <key>INT</key>
                    <name>かしこさ</name>
                    <value>1</value>
                </value>
            </entry>
        </status>
        <items>
            <formula/>
            <name>やくそう</name>
        </items>
        <items>
            <formula/>
            <name>どくそう</name>
        </items>
        <items>
            <formula/>
            <name>プロテイン</name>
        </items>
        <state>
            <key>Normal</key>
        </state>
        <wepon>
            <formula/>
            <name>どうのつるぎ</name>
            <value>12</value>
        </wepon>
        <armor>
            <formula/>
            <name>どうのよろい</name>
            <value>7</value>
        </armor>
    </player>
    <player>
        <level>0</level>
        <name>オルト＝キー</name>
        <sex>MAN</sex>
        <status>
            <entry>
                <key>LV</key>
                <value>
                    <key>LV</key>
                    <name>レベル</name>
                    <value>1</value>
                </value>
            </entry>
            <entry>
                <key>MP</key>
                <value>
                    <key>MP</key>
                    <name>マジックトポイント</name>
                    <value>12</value>
                </value>
            </entry>
            <entry>
                <key>AGI</key>
                <value>
                    <key>AGI</key>
                    <name>すばやさ</name>
                    <value>4</value>
                </value>
            </entry>
            <entry>
                <key>LUK</key>
                <value>
                    <key>LUK</key>
                    <name>うんのよさ</name>
                    <value>10</value>
                </value>
            </entry>
            <entry>
                <key>HP</key>
                <value>
                    <key>HP</key>
                    <name>ヒットポイント</name>
                    <value>12</value>
                </value>
            </entry>
            <entry>
                <key>POW</key>
                <value>
                    <key>POW</key>
                    <name>ちから</name>
                    <value>6</value>
                </value>
            </entry>
            <entry>
                <key>INT</key>
                <value>
                    <key>INT</key>
                    <name>かしこさ</name>
                    <value>1</value>
                </value>
            </entry>
        </status>
        <items>
            <formula/>
            <name>やくそう</name>
        </items>
        <items>
            <formula/>
            <name>どくそう</name>
        </items>
        <items>
            <formula/>
            <name>プロテイン</name>
        </items>
        <state>
            <key>Normal</key>
        </state>
        <wepon>
            <formula/>
            <name>どうのつるぎ</name>
            <value>12</value>
        </wepon>
        <armor>
            <formula/>
            <name>どうのよろい</name>
            <value>7</value>
        </armor>
    </player>
        <player>
        <level>0</level>
        <name>ナム＝ロック</name>
        <sex>MAN</sex>
        <status>
            <entry>
                <key>LV</key>
                <value>
                    <key>LV</key>
                    <name>レベル</name>
                    <value>1</value>
                </value>
            </entry>
            <entry>
                <key>MP</key>
                <value>
                    <key>MP</key>
                    <name>マジックトポイント</name>
                    <value>12</value>
                </value>
            </entry>
            <entry>
                <key>AGI</key>
                <value>
                    <key>AGI</key>
                    <name>すばやさ</name>
                    <value>4</value>
                </value>
            </entry>
            <entry>
                <key>LUK</key>
                <value>
                    <key>LUK</key>
                    <name>うんのよさ</name>
                    <value>10</value>
                </value>
            </entry>
            <entry>
                <key>HP</key>
                <value>
                    <key>HP</key>
                    <name>ヒットポイント</name>
                    <value>12</value>
                </value>
            </entry>
            <entry>
                <key>POW</key>
                <value>
                    <key>POW</key>
                    <name>ちから</name>
                    <value>6</value>
                </value>
            </entry>
            <entry>
                <key>INT</key>
                <value>
                    <key>INT</key>
                    <name>かしこさ</name>
                    <value>1</value>
                </value>
            </entry>
        </status>
        <items>
            <formula/>
            <name>やくそう</name>
        </items>
        <items>
            <formula/>
            <name>どくそう</name>
        </items>
        <items>
            <formula/>
            <name>プロテイン</name>
        </items>
        <state>
            <key>Normal</key>
        </state>
        <wepon>
            <formula/>
            <name>どうのつるぎ</name>
            <value>12</value>
        </wepon>
        <armor>
            <formula/>
            <name>どうのよろい</name>
            <value>7</value>
        </armor>
    </player>
</players>
